here_env.py
here_env-0.2.1.dist-info/entry_points.txt
here_env-0.2.1.dist-info/LICENSE
here_env-0.2.1.dist-info/WHEEL
here_env-0.2.1.dist-info/METADATA
here_env-0.2.1.dist-info/RECORD
